onnxruntime_extensions/__init__.py
onnxruntime_extensions/_cuops.py
onnxruntime_extensions/_extensions_pydll.cp38-win_amd64.pyd
onnxruntime_extensions/_extensions_pydll.pyi
onnxruntime_extensions/_hf_cvt.py
onnxruntime_extensions/_ocos.py
onnxruntime_extensions/_ortapi2.py
onnxruntime_extensions/_torch_cvt.py
onnxruntime_extensions/_version.py
onnxruntime_extensions/cmd.py
onnxruntime_extensions/cvt.py
onnxruntime_extensions/pp_api.py
onnxruntime_extensions/util.py
onnxruntime_extensions/onnxprocess/__init__.py
onnxruntime_extensions/onnxprocess/_builder.py
onnxruntime_extensions/onnxprocess/_onnx_ops.py
onnxruntime_extensions/onnxprocess/_session.py
onnxruntime_extensions/onnxprocess/_tensor.py
onnxruntime_extensions/onnxprocess/torch_wrapper.py
onnxruntime_extensions/pnp/__init__.py
onnxruntime_extensions/pnp/_base.py
onnxruntime_extensions/pnp/_imagenet.py
onnxruntime_extensions/pnp/_nlp.py
onnxruntime_extensions/pnp/_onnx_ops.py
onnxruntime_extensions/pnp/_torchext.py
onnxruntime_extensions/pnp/_unifier.py
onnxruntime_extensions/pnp/_utils.py
onnxruntime_extensions/tools/__init__.py
onnxruntime_extensions/tools/add_HuggingFace_CLIPImageProcessor_to_model.py
onnxruntime_extensions/tools/add_pre_post_processing_to_model.py
onnxruntime_extensions/tools/pre_post_processing/__init__.py
onnxruntime_extensions/tools/pre_post_processing/pre_post_processor.py
onnxruntime_extensions/tools/pre_post_processing/step.py
onnxruntime_extensions/tools/pre_post_processing/utils.py
onnxruntime_extensions/tools/pre_post_processing/steps/__init__.py
onnxruntime_extensions/tools/pre_post_processing/steps/general.py
onnxruntime_extensions/tools/pre_post_processing/steps/nlp.py
onnxruntime_extensions/tools/pre_post_processing/steps/vision.py
onnxruntime_extensions-0.14.0.dist-info/LICENSE
onnxruntime_extensions-0.14.0.dist-info/METADATA
onnxruntime_extensions-0.14.0.dist-info/WHEEL
onnxruntime_extensions-0.14.0.dist-info/top_level.txt
onnxruntime_extensions-0.14.0.dist-info/RECORD
