Metadata-Version: 2.1
Name: onnxruntime_extensions
Version: 0.14.0
Summary: ONNXRuntime Extensions
Home-page: https://github.com/microsoft/onnxruntime-extensions
Author: Microsoft Corporation
Author-email: onnxruntime@microsoft.com
License: MIT License
Classifier: Development Status :: 4 - Beta
Classifier: Environment :: Console
Classifier: Intended Audience :: Developers
Classifier: Operating System :: MacOS :: MacOS X
Classifier: Operating System :: Microsoft :: Windows
Classifier: Operating System :: POSIX :: Linux
Classifier: Programming Language :: C++
Classifier: Programming Language :: Python
Classifier: Programming Language :: Python :: Implementation :: CPython
Classifier: License :: OSI Approved :: MIT License
License-File: LICENSE
